pyFilmFinder/__init__.py
pyFilmFinder/__main__.py
pyFilmFinder/finder.py
pyFilmFinder-0.0.1.dist-info/LICENSE
pyFilmFinder-0.0.1.dist-info/METADATA
pyFilmFinder-0.0.1.dist-info/WHEEL
pyFilmFinder-0.0.1.dist-info/entry_points.txt
pyFilmFinder-0.0.1.dist-info/top_level.txt
pyFilmFinder-0.0.1.dist-info/RECORD
