Metadata-Version: 2.1
Name: pyFilmFinder
Version: 0.0.1
Summary: A Python package designed to simplify the process of discovering and exploring films.
Author: Eleazar Neri, Terry Qui, Johan Gallardo, Marc Etter
License: GNU GENERAL PUBLIC LICENSE
Project-URL: Homepage, https://github.com/software-students-spring2024/3-python-package-exercise-mjet
Project-URL: Repository, https://github.com/software-students-spring2024/3-python-package-exercise-mjet.git
Project-URL: Bug Tracker, https://github.com/software-students-spring2024/3-python-package-exercise-mjet/issues
Keywords: python,package,tmdb,films
Classifier: Programming Language :: Python :: 3
Classifier: License :: OSI Approved :: GNU General Public License v3 (GPLv3)
Classifier: Operating System :: OS Independent
Requires-Python: >=3.7
License-File: LICENSE
Provides-Extra: dev
Requires-Dist: pytest ; extra == 'dev'
